{
  "id": "105_normal",
  "name": "Marowak",
  "types": [
    "Ground"
  ],
  "dex": 105,
  "stats": {
    "stamina": 155,
    "attack": 144,
    "defence": 186
  },
  "quickMoves": [
    "MUD_SLAP_FAST",
    "ROCK_SMASH_FAST"
  ],
  "chargeMoves": [
    "BONE_CLUB",
    "DIG",
    "EARTHQUAKE"
  ],
  "forms": [
    {
      "name": "Normal",
      "code": "normal"
    }
  ],
  "images": {
    "normal": {
      "url": "images/105_normal.png",
      "width": 97,
      "height": 136
    },
    "shiny": {
      "url": "images/105_normal_shiny.png",
      "width": 97,
      "height": 136
    },
    "normalAnimated": {
      "url": "images/105_normal.gif",
      "width": 47,
      "height": 67
    },
    "shinyAnimated": {
      "url": "images/105_normal_shiny.gif",
      "width": 47,
      "height": 67
    }
  }
}