{"id":193,"form":"","image":{"path":"pokemon/193.png","width":120,"height":120},"name":"Yanma","types":[{"name":"Bug","effectiveness":{"Normal":{"description":"normal effectiveness","multiplier":1},"Fire":{"description":"not very effective","multiplier":0.63},"Water":{"description":"normal effectiveness","multiplier":1},"Electric":{"description":"normal effectiveness","multiplier":1},"Grass":{"description":"super-effective","multiplier":1.6},"Ice":{"description":"normal effectiveness","multiplier":1},"Fighting":{"description":"not very effective","multiplier":0.63},"Poison":{"description":"not very effective","multiplier":0.63},"Ground":{"description":"normal effectiveness","multiplier":1},"Flying":{"description":"not very effective","multiplier":0.63},"Psychic":{"description":"super-effective","multiplier":1.6},"Bug":{"description":"normal effectiveness","multiplier":1},"Rock":{"description":"normal effectiveness","multiplier":1},"Ghost":{"description":"not very effective","multiplier":0.63},"Dragon":{"description":"normal effectiveness","multiplier":1},"Dark":{"description":"super-effective","multiplier":1.6},"Steel":{"description":"not very effective","multiplier":0.63},"Fairy":{"description":"not very effective","multiplier":0.63}}},{"name":"Flying","effectiveness":{"Normal":{"description":"normal effectiveness","multiplier":1},"Fire":{"description":"normal effectiveness","multiplier":1},"Water":{"description":"normal effectiveness","multiplier":1},"Electric":{"description":"not very effective","multiplier":0.63},"Grass":{"description":"super-effective","multiplier":1.6},"Ice":{"description":"normal effectiveness","multiplier":1},"Fighting":{"description":"super-effective","multiplier":1.6},"Poison":{"description":"normal effectiveness","multiplier":1},"Ground":{"description":"normal effectiveness","multiplier":1},"Flying":{"description":"normal effectiveness","multiplier":1},"Psychic":{"description":"normal effectiveness","multiplier":1},"Bug":{"description":"super-effective","multiplier":1.6},"Rock":{"description":"not very effective","multiplier":0.63},"Ghost":{"description":"normal effectiveness","multiplier":1},"Dragon":{"description":"normal effectiveness","multiplier":1},"Dark":{"description":"normal effectiveness","multiplier":1},"Steel":{"description":"not very effective","multiplier":0.63},"Fairy":{"description":"normal effectiveness","multiplier":1}}}],"stats":{"hp":163,"attack":154,"defence":94},"moves":[{"name":"Quick Attack","type":"normal","damage":8,"duration":0.8,"energy":10,"damagePVP":5,"energyPVP":7,"durationPVP":1,"category":"fast"},{"name":"Wing Attack","type":"flying","damage":8,"duration":0.8,"energy":9,"damagePVP":5,"energyPVP":7,"durationPVP":1,"category":"fast"},{"name":"Ancient Power","type":"rock","damage":70,"duration":3.5,"energy":3,"damagePVP":45,"energyPVP":45,"durationPVP":3.5,"category":"charge"},{"name":"Aerial Ace","type":"flying","damage":55,"duration":2.4,"energy":3,"damagePVP":55,"energyPVP":45,"durationPVP":2.4,"category":"charge"},{"name":"Silver Wind","type":"bug","damage":70,"duration":3.7,"energy":3,"damagePVP":45,"energyPVP":45,"durationPVP":3.7,"category":"charge"}]}