{
  "id": "258_normal",
  "name": "Mudkip",
  "types": [
    "Water"
  ],
  "number": 258,
  "stats": {
    "stamina": 137,
    "attack": 126,
    "defence": 93
  },
  "quickMoves": [
    "TACKLE_FAST",
    "WATER_GUN_FAST"
  ],
  "chargeMoves": [
    "DIG",
    "SLUDGE",
    "STOMP"
  ],
  "forms": [
    {
      "name": "Normal",
      "code": "normal"
    }
  ],
  "images": {
    "normal": {
      "url": "images/258_normal.png",
      "width": 58,
      "height": 81
    },
    "shiny": {
      "url": "images/258_normal_shiny.png",
      "width": 58,
      "height": 81
    },
    "normalAnimated": {
      "url": "images/258_normal.gif",
      "width": 47,
      "height": 66
    },
    "shinyAnimated": {
      "url": "images/258_normal_shiny.gif",
      "width": 47,
      "height": 66
    }
  }
}