{"id":"276","number":276,"name":"Taillow","form":null,"types":[{"name":"Normal","effectiveness":{"Normal":{"description":"normal effectiveness","multiplier":1},"Fire":{"description":"normal effectiveness","multiplier":1},"Water":{"description":"normal effectiveness","multiplier":1},"Electric":{"description":"normal effectiveness","multiplier":1},"Grass":{"description":"normal effectiveness","multiplier":1},"Ice":{"description":"normal effectiveness","multiplier":1},"Fighting":{"description":"normal effectiveness","multiplier":1},"Poison":{"description":"normal effectiveness","multiplier":1},"Ground":{"description":"normal effectiveness","multiplier":1},"Flying":{"description":"normal effectiveness","multiplier":1},"Psychic":{"description":"normal effectiveness","multiplier":1},"Bug":{"description":"normal effectiveness","multiplier":1},"Rock":{"description":"not very effective","multiplier":0.63},"Ghost":{"description":"double resistance","multiplier":0.39},"Dragon":{"description":"normal effectiveness","multiplier":1},"Dark":{"description":"normal effectiveness","multiplier":1},"Steel":{"description":"not very effective","multiplier":0.63},"Fairy":{"description":"normal effectiveness","multiplier":1}}},{"name":"Flying","effectiveness":{"Normal":{"description":"normal effectiveness","multiplier":1},"Fire":{"description":"normal effectiveness","multiplier":1},"Water":{"description":"normal effectiveness","multiplier":1},"Electric":{"description":"not very effective","multiplier":0.63},"Grass":{"description":"super-effective","multiplier":1.6},"Ice":{"description":"normal effectiveness","multiplier":1},"Fighting":{"description":"super-effective","multiplier":1.6},"Poison":{"description":"normal effectiveness","multiplier":1},"Ground":{"description":"normal effectiveness","multiplier":1},"Flying":{"description":"normal effectiveness","multiplier":1},"Psychic":{"description":"normal effectiveness","multiplier":1},"Bug":{"description":"super-effective","multiplier":1.6},"Rock":{"description":"not very effective","multiplier":0.63},"Ghost":{"description":"normal effectiveness","multiplier":1},"Dragon":{"description":"normal effectiveness","multiplier":1},"Dark":{"description":"normal effectiveness","multiplier":1},"Steel":{"description":"not very effective","multiplier":0.63},"Fairy":{"description":"normal effectiveness","multiplier":1}}}],"generation":3,"stats":{"attack":106,"defence":61,"hp":120},"images":[{"url":"https://raw.githubusercontent.com/trs/pokemon-data-deno/main/public/images/normal/276.gif","path":"images/normal/276.gif","type":"gif","category":"model","width":49,"height":46,"variant":"normal"},{"url":"https://raw.githubusercontent.com/trs/pokemon-data-deno/main/public/images/shiny/276.gif","path":"images/shiny/276.gif","type":"gif","category":"model","width":49,"height":46,"variant":"shiny"},{"url":"https://raw.githubusercontent.com/trs/pokemon-data-deno/main/public/images/normal/276.png","path":"images/normal/276.png","type":"png","category":"model","width":256,"height":256,"variant":"normal"},{"url":"https://raw.githubusercontent.com/trs/pokemon-data-deno/main/public/images/shiny/276.png","path":"images/shiny/276.png","type":"png","category":"model","width":256,"height":256,"variant":"shiny"}]}