{
  "id": "279_normal",
  "name": "Pelipper",
  "types": [
    "Water",
    "Flying"
  ],
  "dex": 279,
  "stats": {
    "stamina": 155,
    "attack": 175,
    "defence": 174
  },
  "quickMoves": [
    "WATER_GUN_FAST",
    "WING_ATTACK_FAST"
  ],
  "chargeMoves": [
    "HYDRO_PUMP",
    "HURRICANE",
    "BLIZZARD",
    "WEATHER_BALL_WATER"
  ],
  "forms": [
    {
      "name": "Normal",
      "code": "normal"
    }
  ],
  "images": {
    "normal": {
      "url": "images/279_normal.png",
      "width": 224,
      "height": 143
    },
    "shiny": {
      "url": "images/279_normal_shiny.png",
      "width": 224,
      "height": 143
    },
    "normalAnimated": {
      "url": "images/279_normal.gif",
      "width": 101,
      "height": 92
    },
    "shinyAnimated": {
      "url": "images/279_normal_shiny.gif",
      "width": 101,
      "height": 92
    }
  }
}