{"id":364,"form":"","image":{"path":"pokemon/364.png","width":120,"height":120},"name":"Sealeo","types":[{"name":"Ice","effectiveness":{"Normal":{"description":"normal effectiveness","multiplier":1},"Fire":{"description":"not very effective","multiplier":0.63},"Water":{"description":"not very effective","multiplier":0.63},"Electric":{"description":"normal effectiveness","multiplier":1},"Grass":{"description":"super-effective","multiplier":1.6},"Ice":{"description":"not very effective","multiplier":0.63},"Fighting":{"description":"normal effectiveness","multiplier":1},"Poison":{"description":"normal effectiveness","multiplier":1},"Ground":{"description":"super-effective","multiplier":1.6},"Flying":{"description":"super-effective","multiplier":1.6},"Psychic":{"description":"normal effectiveness","multiplier":1},"Bug":{"description":"normal effectiveness","multiplier":1},"Rock":{"description":"normal effectiveness","multiplier":1},"Ghost":{"description":"normal effectiveness","multiplier":1},"Dragon":{"description":"super-effective","multiplier":1.6},"Dark":{"description":"normal effectiveness","multiplier":1},"Steel":{"description":"not very effective","multiplier":0.63},"Fairy":{"description":"normal effectiveness","multiplier":1}}},{"name":"Water","effectiveness":{"Normal":{"description":"normal effectiveness","multiplier":1},"Fire":{"description":"super-effective","multiplier":1.6},"Water":{"description":"not very effective","multiplier":0.63},"Electric":{"description":"normal effectiveness","multiplier":1},"Grass":{"description":"not very effective","multiplier":0.63},"Ice":{"description":"normal effectiveness","multiplier":1},"Fighting":{"description":"normal effectiveness","multiplier":1},"Poison":{"description":"normal effectiveness","multiplier":1},"Ground":{"description":"super-effective","multiplier":1.6},"Flying":{"description":"normal effectiveness","multiplier":1},"Psychic":{"description":"normal effectiveness","multiplier":1},"Bug":{"description":"normal effectiveness","multiplier":1},"Rock":{"description":"super-effective","multiplier":1.6},"Ghost":{"description":"normal effectiveness","multiplier":1},"Dragon":{"description":"not very effective","multiplier":0.63},"Dark":{"description":"normal effectiveness","multiplier":1},"Steel":{"description":"normal effectiveness","multiplier":1},"Fairy":{"description":"normal effectiveness","multiplier":1}}}],"stats":{"hp":207,"attack":137,"defence":132},"moves":[{"name":"Water Gun","type":"water","damage":5,"duration":0.5,"energy":6,"damagePVP":3,"energyPVP":3,"durationPVP":0.5,"category":"fast"},{"name":"Powder Snow","type":"ice","damage":6,"duration":1,"energy":15,"damagePVP":5,"energyPVP":8,"durationPVP":1,"category":"fast"},{"name":"Aurora Beam","type":"ice","damage":80,"duration":3.55,"energy":2,"damagePVP":80,"energyPVP":60,"durationPVP":3.55,"category":"charge"},{"name":"Body Slam","type":"normal","damage":50,"duration":1.9,"energy":3,"damagePVP":60,"energyPVP":35,"durationPVP":1.9,"category":"charge"},{"name":"Water Pulse","type":"water","damage":70,"duration":3.2,"energy":2,"damagePVP":70,"energyPVP":60,"durationPVP":3.2,"category":"charge"}],"key":"364"}