{
  "id": "372_normal",
  "name": "Shelgon",
  "types": [
    "Dragon"
  ],
  "dex": 372,
  "stats": {
    "stamina": 163,
    "attack": 172,
    "defence": 155
  },
  "quickMoves": [
    "EMBER_FAST",
    "DRAGON_BREATH_FAST"
  ],
  "chargeMoves": [
    "FLAMETHROWER",
    "DRAGON_PULSE",
    "TWISTER"
  ],
  "forms": [
    {
      "name": "Normal",
      "code": "normal"
    }
  ],
  "images": {
    "normal": {
      "url": "images/372_normal.png",
      "width": 137,
      "height": 147
    },
    "shiny": {
      "url": "images/372_normal_shiny.png",
      "width": 137,
      "height": 147
    },
    "normalAnimated": {
      "url": "images/372_normal.gif",
      "width": 57,
      "height": 59
    },
    "shinyAnimated": {
      "url": "images/372_normal_shiny.gif",
      "width": 57,
      "height": 59
    }
  }
}