{"id":"53-alola","number":53,"forms":[{"name":"Alola","code":"alola","id":"alola"}],"images":[{"type":"png","variant":"normal","url":"https://www.serebii.net/pokemongo/pokemon/053-a.png"},{"type":"gif","variant":"normal","url":"https://projectpokemon.org/images/normal-sprite/persian-alola.gif"},{"type":"gif","variant":"shiny","url":"https://projectpokemon.org/images/shiny-sprite/persian-alola.gif"}],"name":"Persian","types":[{"name":"Dark","effectiveness":{"Normal":{"description":"normal effectiveness","multiplier":1},"Fire":{"description":"normal effectiveness","multiplier":1},"Water":{"description":"normal effectiveness","multiplier":1},"Electric":{"description":"normal effectiveness","multiplier":1},"Grass":{"description":"normal effectiveness","multiplier":1},"Ice":{"description":"normal effectiveness","multiplier":1},"Fighting":{"description":"not very effective","multiplier":0.63},"Poison":{"description":"normal effectiveness","multiplier":1},"Ground":{"description":"normal effectiveness","multiplier":1},"Flying":{"description":"normal effectiveness","multiplier":1},"Psychic":{"description":"super-effective","multiplier":1.6},"Bug":{"description":"normal effectiveness","multiplier":1},"Rock":{"description":"normal effectiveness","multiplier":1},"Ghost":{"description":"super-effective","multiplier":1.6},"Dragon":{"description":"normal effectiveness","multiplier":1},"Dark":{"description":"not very effective","multiplier":0.63},"Steel":{"description":"normal effectiveness","multiplier":1},"Fairy":{"description":"not very effective","multiplier":0.63}}}],"stats":{"hp":163,"attack":158,"defence":136},"moves":[{"name":"Scratch","type":"normal","damage":6,"duration":0.5,"energy":4,"damagePVP":4,"energyPVP":2,"durationPVP":0.5,"category":"fast"},{"name":"Feint Attack","type":"dark","damage":10,"duration":0.9,"energy":9,"damagePVP":6,"energyPVP":6,"durationPVP":1,"category":"fast"},{"name":"Foul Play","type":"dark","damage":70,"duration":2,"energy":2,"damagePVP":70,"energyPVP":45,"durationPVP":2,"category":"charge"},{"name":"Dark Pulse","type":"dark","damage":80,"duration":3,"energy":2,"damagePVP":80,"energyPVP":50,"durationPVP":3,"category":"charge"},{"name":"Play Rough","type":"fairy","damage":90,"duration":2.9,"energy":2,"damagePVP":90,"energyPVP":60,"durationPVP":2.9,"category":"charge"}],"image":{"normal":{"png":{"path":"api/pokemon/normal/53-alola.png","width":120,"height":120},"gif":{"path":"api/pokemon/normal/53-alola.gif","width":18759,"height":14406}},"shiny":{"gif":{"path":"api/pokemon/shiny/53-alola.gif","width":18759,"height":14406}}}}