{
  "id": "53",
  "name": "Persian",
  "types": [
    "Normal"
  ],
  "number": 53,
  "stats": {
    "stamina": 163,
    "attack": 150,
    "defence": 136
  },
  "quickMoves": [
    "SCRATCH_FAST",
    "FEINT_ATTACK_FAST"
  ],
  "chargeMoves": [
    "FOUL_PLAY",
    "POWER_GEM",
    "PLAY_ROUGH"
  ],
  "forms": [
    {
      "name": "Normal",
      "code": "normal"
    }
  ],
  "images": {
    "normal": {
      "url": "img/53.png",
      "width": 184,
      "height": 134
    },
    "shiny": {
      "url": "img/53_shiny.png",
      "width": 184,
      "height": 134
    },
    "normalAnimated": {
      "url": "img/53.gif",
      "width": 61,
      "height": 70
    },
    "shinyAnimated": {
      "url": "img/53_shiny.gif",
      "width": 61,
      "height": 70
    }
  }
}