{
  "id": "644_normal",
  "name": "Zekrom",
  "types": [
    "Dragon",
    "Electric"
  ],
  "dex": 644,
  "stats": {
    "stamina": 205,
    "attack": 275,
    "defence": 211
  },
  "quickMoves": [
    "DRAGON_BREATH_FAST",
    "CHARGE_BEAM_FAST"
  ],
  "chargeMoves": [
    "OUTRAGE",
    "WILD_CHARGE",
    "FLASH_CANNON",
    "CRUNCH"
  ],
  "forms": [
    "Normal"
  ],
  "images": {
    "normal": {
      "url": "images/644_normal.png",
      "width": 240,
      "height": 240
    },
    "shiny": {
      "url": "images/644_normal_shiny.png",
      "width": 240,
      "height": 240
    },
    "normalAnimated": {
      "url": "images/644_normal.gif",
      "width": 116,
      "height": 136
    },
    "shinyAnimated": {
      "url": "images/644_normal_shiny.gif",
      "width": 116,
      "height": 136
    }
  }
}