{
  "id": "646_white",
  "name": "Kyurem",
  "types": [
    "Dragon",
    "Ice"
  ],
  "dex": 646,
  "stats": {
    "stamina": 245,
    "attack": 310,
    "defence": 183
  },
  "quickMoves": [
    "DRAGON_BREATH_FAST",
    "STEEL_WING_FAST"
  ],
  "chargeMoves": [
    "DRAGON_PULSE",
    "BLIZZARD",
    "ANCIENT_POWER",
    "FOCUS_BLAST"
  ],
  "forms": [
    "White"
  ],
  "images": {
    "normal": {
      "url": "images/646_white.png",
      "width": 220,
      "height": 199
    },
    "shiny": {
      "url": "images/646_white_shiny.png",
      "width": 220,
      "height": 199
    },
    "normalAnimated": {
      "url": "images/646_white.gif",
      "width": 136,
      "height": 131
    },
    "shinyAnimated": {
      "url": "images/646_white_shiny.gif",
      "width": 136,
      "height": 131
    }
  }
}